py_identity_model/token_client.py
py_identity_model/discovery.py
py_identity_model/__init__.py
py_identity_model/jwks.py
py_identity_model/exceptions.py
py_identity_model/token_validation.py
py_identity_model/validation/__init__.py
py_identity_model/validation/validation_result.py
py_identity_model/validation/state_validation_result.py
py_identity_model-1.0.0.dist-info/WHEEL
py_identity_model-1.0.0.dist-info/METADATA
py_identity_model-1.0.0.dist-info/RECORD
