Metadata-Version: 2.3
Name: py-identity-model
Version: 1.0.0
Summary: OAuth2.0 and OpenID Connect Client Library
Author: jamescrowley321
Author-email: jamescrowley321 <jamescrowley151@gmail.com>
Classifier: License :: OSI Approved :: Apache Software License
Requires-Dist: pyjwt>=2.9.0,<3
Requires-Dist: requests>=2.32.3,<3
Requires-Dist: cryptography>=45.0.2,<46
Requires-Python: ~=3.12
